babylonrsa/__init__.py
babylonrsa/base60.py
babylonrsa/cli.py
babylonrsa/primes.py
babylonrsa/rsa.py
babylonrsa-1.0.0.dist-info/METADATA
babylonrsa-1.0.0.dist-info/WHEEL
babylonrsa-1.0.0.dist-info/entry_points.txt
babylonrsa-1.0.0.dist-info/top_level.txt
babylonrsa-1.0.0.dist-info/RECORD
